deatrisdev/__init__.py
deatrisdev/deatrisdev.py
deatrisdev-0.2.dist-info/METADATA
deatrisdev-0.2.dist-info/WHEEL
deatrisdev-0.2.dist-info/top_level.txt
deatrisdev-0.2.dist-info/RECORD
